<?xml version="1.0" encoding="UTF-8"?>
<resource xmlns="http://datacite.org/schema/kernel-3" xmlns:xsi="http://www.w3.org/2001/XMLSchema-instance" xmlns:jats="http://www.ncbi.nlm.nih.gov/JATS1" xmlns:ai="http://www.crossref.org/AccessIndicators.xsd" xsi:schemaLocation="http://datacite.org/schema/kernel-3 http://schema.datacite.org/meta/kernel-3/metadata.xsd"><identifier identifierType="DOI">10.26493/1855-3974.19_2</identifier><creators><creator><creatorName>ARS MATHEMATICA CONTEMPORANEA</creatorName></creator></creators><titles><title>ARS MATHEMATICA CONTEMPORANEA, Vol 19, No 2 (2020)</title></titles><publisher>ARS MATHEMATICA CONTEMPORANEA</publisher><publicationYear>2020</publicationYear><dates><date dateType="Issued">2020-10-28</date></dates><language>en</language><resourceType resourceTypeGeneral="Text">Journal Issue</resourceType><alternateIdentifiers><alternateIdentifier alternateIdentifierType="publisherId">1-45</alternateIdentifier><alternateIdentifier alternateIdentifierType="EISSN">1855-3974</alternateIdentifier><alternateIdentifier alternateIdentifierType="ISSN">1855-3966</alternateIdentifier></alternateIdentifiers><relatedIdentifiers><relatedIdentifier relatedIdentifierType="DOI" relationType="HasPart">10.26493/1855-3974.1849.148</relatedIdentifier><relatedIdentifier relatedIdentifierType="DOI" relationType="HasPart">10.26493/1855-3974.1851.b44</relatedIdentifier><relatedIdentifier relatedIdentifierType="DOI" relationType="HasPart">10.26493/1855-3974.2022.44a</relatedIdentifier><relatedIdentifier relatedIdentifierType="DOI" relationType="HasPart">10.26493/1855-3974.2033.974</relatedIdentifier><relatedIdentifier relatedIdentifierType="DOI" relationType="HasPart">10.26493/1855-3974.2039.efc</relatedIdentifier><relatedIdentifier relatedIdentifierType="DOI" relationType="HasPart">10.26493/1855-3974.2096.c9d</relatedIdentifier><relatedIdentifier relatedIdentifierType="DOI" relationType="HasPart">10.26493/1855-3974.2103.e84</relatedIdentifier><relatedIdentifier relatedIdentifierType="DOI" relationType="HasPart">10.26493/1855-3974.2122.1e2</relatedIdentifier><relatedIdentifier relatedIdentifierType="DOI" relationType="HasPart">10.26493/1855-3974.2125.7b0</relatedIdentifier><relatedIdentifier relatedIdentifierType="DOI" relationType="HasPart">10.26493/1855-3974.2128.ccf</relatedIdentifier><relatedIdentifier relatedIdentifierType="DOI" relationType="HasPart">10.26493/1855-3974.2262.9b8</relatedIdentifier><relatedIdentifier relatedIdentifierType="DOI" relationType="HasPart">10.26493/1855-3974.2348.f42</relatedIdentifier></relatedIdentifiers><rightsList><rights rightsURI=""></rights></rightsList><descriptions><description descriptionType="TableOfContents">Distinguishing numbers of finite 4-valent vertex-transitive graphs...173-187
Frobenius groups which are the automorphism groups of orientably-regular maps...363-374
Properties of double Roman domination on cardinal products of graphs...337-349
Divergence zero quaternionic vector fields and Hamming graphs...189-208
A Möbius-type gluing technique for obtaining edge-critical graphs...209-229
Distance-balanced graphs and travelling salesman problems...311-324
On the divisibility of binomial coefficients...297-309
On generalized truncations of complete graphs...325-335
On resolving sets in the point-line incidence graph of PG(n, q)...231-247
Building maximal green sequences via component preserving mutations...249-275
On the Smith normal form of Varchenko matrix...351-362
The Cayley isomorphism property for the group C25 × Cp...277-295
ORCID iD</description></descriptions></resource>
